assetic/__init__.py
assetic/__version__.py
assetic/api_client.py
assetic/assetic_sdk.py
assetic/configuration.py
assetic/rest.py
assetic/api/__init__.py
assetic/api/application_feedback_api.py
assetic/api/assessment_form_api.py
assetic/api/assessment_form_result_api.py
assetic/api/assessment_project_api.py
assetic/api/assessment_task_api.py
assetic/api/asset_api.py
assetic/api/asset_configuration_api.py
assetic/api/auth_api.py
assetic/api/background_worker_api.py
assetic/api/component_api.py
assetic/api/data_exchange_job_api.py
assetic/api/data_exchange_task_api.py
assetic/api/dimension_api.py
assetic/api/document_api.py
assetic/api/fcr_categorisation_api.py
assetic/api/functional_location_api.py
assetic/api/maintenance_configuration_api.py
assetic/api/reporting_export_api.py
assetic/api/reporting_view_api.py
assetic/api/resource_api.py
assetic/api/search_api.py
assetic/api/service_criteria_api.py
assetic/api/system_configuration_api.py
assetic/api/version_api.py
assetic/api/work_order_api.py
assetic/api/work_request_api.py
assetic/models/__init__.py
assetic/models/application_create_ticket_representation.py
assetic/models/asmt_form_result_representation.py
assetic/models/asmt_task_form_representation.py
assetic/models/asmt_task_list_representation.py
assetic/models/asmt_task_object_representation.py
assetic/models/asmt_task_representation.py
assetic/models/assembly.py
assetic/models/assessment_form_detail_list_representation.py
assetic/models/assessment_form_detail_representation.py
assetic/models/assessment_form_page_representation.py
assetic/models/assessment_form_tab_representation.py
assetic/models/assessment_project_representation.py
assetic/models/assessment_project_type_representation.py
assetic/models/asset_association_list_representation.py
assetic/models/asset_association_representation.py
assetic/models/asset_association_request_representation.py
assetic/models/asset_attributes_by_category_list_representation.py
assetic-2026.4.1.1.dist-info/LICENSE.txt
assetic-2026.4.1.1.dist-info/METADATA
assetic-2026.4.1.1.dist-info/WHEEL
assetic-2026.4.1.1.dist-info/top_level.txt
assetic-2026.4.1.1.dist-info/RECORD
