Metadata-Version: 2.1
Name: assetic
Version: 2026.4.1.1
Summary: Assetic Integration API
Home-page: http://www.assetic.com
Author-email: developer@assetic.com
Keywords: Assetic Integration APIs
License-File: LICENSE.txt
Requires-Dist: urllib3 >=1.15
Requires-Dist: six >=1.10
Requires-Dist: certifi
Requires-Dist: python-dateutil
Requires-Dist: openpyxl >=2.4.1
Requires-Dist: configparser
Requires-Dist: pyodbc >=4.0.21
Requires-Dist: pandas >=0.12.0
Requires-Dist: keyring
